{"frames": [

{
	"filename": "000None.png",
	"frame": {"x":0,"y":0,"w":40,"h":40},
	"rotated": false,
	"trimmed": false,
	"spriteSourceSize": {"x":0,"y":0,"w":40,"h":40},
	"sourceSize": {"w":40,"h":40}
},
{
	"filename": "001Spawn.png",
	"frame": {"x":40,"y":0,"w":40,"h":40},
	"rotated": false,
	"trimmed": false,
	"spriteSourceSize": {"x":0,"y":0,"w":40,"h":40},
	"sourceSize": {"w":40,"h":40}
}],
"meta": {
	"app": "http://www.texturepacker.com",
	"version": "1.0",
	"image": "metaTiles.png",
	"format": "RGBA8888",
	"size": {"w":80,"h":40},
	"scale": "1",
	"smartupdate": "$TexturePacker:SmartUpdate:f19eb1eddf8168ed9096c9bae3c7c0ff$"
}
}
